README.md
setup.cfg
setup.py
probability_distributions07/Binomialdistribution.py
probability_distributions07/Gaussiandistribution.py
probability_distributions07/Generaldistribution.py
probability_distributions07/__init__.py
probability_distributions07.egg-info/PKG-INFO
probability_distributions07.egg-info/SOURCES.txt
probability_distributions07.egg-info/dependency_links.txt
probability_distributions07.egg-info/not-zip-safe
probability_distributions07.egg-info/top_level.txt